Framex/__init__.py
Framex/frame.py
Framex/imports.py
Framex/objects.py
framex_ce-0.1.0.dist-info/licenses/LICENSE
framex_ce-0.1.0.dist-info/METADATA
framex_ce-0.1.0.dist-info/WHEEL
framex_ce-0.1.0.dist-info/top_level.txt
framex_ce-0.1.0.dist-info/RECORD
