Metadata-Version: 2.4
Name: framex-ce
Version: 0.1.0
Summary: Quick-start framework for pygame-ce prototypes
Author: JK
Requires-Python: >=3.10
License-File: LICENSE
Requires-Dist: pygame-ce
Dynamic: license-file
